{
  "2900": "噂は効いている。味方に天才がいる。心強いな。",
  "2901": "聴いたか? ラボが破壊されたらしい。",
  "2902": "聴いたか? ラボの主人が脱走したらしい。それほどひどい選挙だったことだ。",
  "2903": "先進技術圏の主人が脱走だとよ。頭がイカルトって話もある。",
  "2904": "珍しくないさ。誰だっておかしくなる。今の状況ではな。むしろ、おかしくなった方が楽かもな。",
  "2905": "敵戦団が接近しています!",
  "2906": "敵、大規模戦闘を確認!",
  "2907": "新型の敵戦を撃墜した奴がいるぞ!",
  "2908": "アイツは戦う方法を知ってるんだ!",
  "2909": "敵の弱点を知っている奴がいる。勝てるぞ!",
  "2910": "次回はお楽しみに!",
  "2911": "アイツに続け!",
  "2912": "チームX了解!アイツを援護する!",
  "2913": "さすがストームワンだな!",
  "2914": "アレがストームワンか!",
  "2915": "知ってるか?あの人は運も強い。カードで勝負したが歯が立たなかった。",
  "2916": "さすがストームワンダー!",
  "2917": "強いだけじゃないぞ。アイツのアドバイスで助かった奴は多い。何が起こるかわかっているみたいだ。ベテランの勘って奴だな。",
  "2918": "略語は覚えられない。EMC、何の略だ?",
  "2919": "確か、エレクトリカル・メーサー・キャノン?",
  "2920": "エレクトロマグネティック・マテリアルクロプサーだ。",
  "2921": "よし!EMCでいい!",
  "2922": "オメガより全世界へ!我ら勝利せり!",
  "2923": "作戦成功だ!",
  "2924": "新類はやったぞー!",
  "2925": "戦局報道です。世界各地で戦闘が続いており、我々の損害は日々増え続けています。しかし、EDFの反撃により敵側の損害も大きくなっている状況です。敵は母星から遠く離れ、次第に消耗しつつあります。戦いは優勢に進んでいます。",
  "2926": "戦局報道です。世界各地で戦闘が続いており、我々の損害は日々増え続けています。しかし、EDFの反撃により敵側の損害も大きくなっている状況です。敵は母星から遠く離れ、次第に消耗しつつあります。戦いは優勢に進んでいます。",
  "2927": "スキュラはかなりの大群です。こんな規模の群れはほとんど確認されていません。",
  "2928": "何かがスキュラを呼び集めているのかも。",
  "2929": "本当にタイムマシンがあるって言うんですか?",
  "2930": "本当にタイムマシンがあるって言うんですか?",
  "2931": "タイムマシン、本当だったんですね。",
  "2932": "敵戦からアンドロイドが効果。",
  "2933": "敵戦はアンドロイドを投下し続けています。",
  "2934": "敵戦からエイリアンが降下。",
  "2935": "船が接近しています。",
  "2936": "本当にタイムマシンがあるなんて!",
  "2937": "大型アンドロイドは中華機を装備しています。距離をとって戦ってください。",
  "2938": "弱点を守るシールだ。歩兵の接近を防ぐための武装。",
  "2939": "空戦じゃない! 意図的な改良です!プライマーは人類の戦い方に合わせて武器を改良してる!",
  "2940": "空船のわけない。最初は人類をあなどっていたんです。でも、反撃を受けたから改良した。新しいサッチュサイを作るようなものです。",
  "2941": "プライマーは人類と戦っているわけじゃない。効率よく駆除する方法を模索しているだけなんです!",
  "2942": "信じられない。敵の計画の上を行くなんて!",
  "2943": "黄色い球体がグレネードです。グレネードを狙ってください。",
  "2944": "グレネードを狙い撃つことで、擲弾兵ごと爆破できるはずです。ただ、爆発に巻き込まれないよう、十分に距離をとってください。",
  "2945": "グレネードの爆発を利用し、周囲の敵を巻き込んだ例があります。密集した敵の中に擲弾兵がいた場合、グレネードを狙うことで、まとめて破壊できるかもしれません。",
  "2946": "アンドロイド本体を破壊すれば、地面に落ちます。落ちたグレネードは数秒後に爆発するようですが、ともかく、多少の時間が稼げます。擲弾兵に接近された場合は、グレネードではなく、本体を攻撃。起爆するまでに退避してください。",
  "2947": "擲弾兵、多数出現。数が多すぎます。こんな!",
  "2948": "この作品は非常に悪いです。",
  "2949": "プライマーは地球環境を壊さず、人間だけを消そうとしていました。でも、やり方を変えたんです。なりふり構わず、爆弾で吹き飛ばそうとしてる!",
  "2950": "高機動型です。高機動型アンドロイドを確認しました。",
  "2951": "空中機動型です。空中機動型アンドロイドを確認しました。",
  "2952": "重装型です。重装アンドロイドを確認しました。",
  "2953": "チームと合流してください。",
  "2954": "ガンマ型を確認!",
  "2955": "振動を検知、ガンマ型の群れだと思われます。",
  "2956": "こちらで映像をモニターしています。地下に何があるのか。それが分かれば、この任務は成功です。",
  "2957": "もっと映像を接近してください。",
  "2958": "空軍から連絡、誘導は成功です。未確認生物が来ます。",
  "2959": "目標接近!",
  "2960": "この生物の体調はエルギヌスの2倍です。こんな巨体で空を飛べなんて!",
  "2961": "エルギヌスは脅威ではありましたが、進路は予測可能で、移動エリアも限定されていました。だからこそ被害は限られていたのですが、飛べるとなると。",
  "2962": "空軍の攻撃です。",
  "2963": "3、2、1、攻撃来ます!",
  "2964": "3、2、1、来ます!",
  "2965": "攻撃のため、装甲を開く瞬間があるはずです。危険ですが、開いた装甲の内部を狙えば破壊できます。",
  "2966": "軽撃する備えはありません。攻撃せず通過させましょう。",
  "2967": "サイレン、低空飛行で開い、攻撃は避けて下さい。",
  "2968": "サイレンは何かに追跡されているようです。",
  "2969": "移動部隊あり、海です!",
  "2970": "わかりません。警戒してください。",
  "2971": "周囲の海岸に次々と水生生物が上陸しています。",
  "2972": "銃弾が効くというデータは?",
  "2973": "例の主人ですね。",
  "2974": "周囲の温度が上昇しています。サイレンの体温によるものだと思われます。",
  "2975": "サイレンの皮膚はかなりの高温です。これで生きているなんて。",
  "2976": "サイレンはエネルギーを放出し続けています。この状態が続くなんて!",
  "2977": "サイレン、移動を始めました!",
  "2978": "すでに攻撃機はサイレンを追跡しています。",
  "2979": "パンドラ、期間以上のため動けません!",
  "2980": "精錬、期間以上のため動けません!",
  "2981": "マザーシップに着弾!",
  "2982": "マザーシップに損傷を与えたようです。",
  "2983": "エイリアン接近!",
  "2984": "クルールが接近中!",
  "2985": "ポイントCにエイリアンが進行中。ガンシップに砲撃を要請しました。",
  "2986": "スタンシップ、砲撃します!",
  "2987": "スカンシップ攻撃開始!",
  "2988": "敵の第2体が接近!",
  "2989": "超大型アンドロイド確認!",
  "2990": "敵降下点を確認!",
  "2991": "次回はお楽しみに!",
  "2992": "怪物が来ます!",
  "2993": "解読者のみなさん、ご視聴ありがとうございました。",
  "2994": "敵の降下点が接近!",
  "2995": "トロップシップ接近!",
  "2996": "エイリアンが降下します。",
  "2997": "高架で、さらに接近!",
  "2998": "多数の敵が作戦エリアに向かっています。",
  "2999": "数が多すぎます。"
}
