{
  "8300": "巨大モグラか。きっと可愛いぞ。",
  "8301": "噂は間違ってなかった。認めよう。お前は勇士だ。",
  "8302": "これらが隠していたのはこの地底庫か。どういうことなんだ。",
  "8303": "暗闇に何かいるぞ!出会い!",
  "8304": "フゥー!",
  "8305": "フゥー!",
  "8306": "あの怪物はなんだ?",
  "8307": "次回はお楽しみに!",
  "8308": "怪物のくせに巨体の生かし方をわかってる。",
  "8309": "次回予告",
  "8310": "この掛け声は、タイアタリで相手を潰すつもりです。",
  "8311": "こちら、ウィングダイバー。戦闘開始する。",
  "8312": "よく持ちこたえたな。エンゴス!",
  "8313": "楽しんでるようだな。付き合おう!",
  "8314": "ロボットは予想以上の数です。援護を送ってください。",
  "8315": "協力すればロボットを倒せる。市民を救うんだ!",
  "8316": "次回はお楽しみに!",
  "8317": "不法侵入!",
  "8318": "次回予告",
  "8319": "ご視聴ありがとうございました。",
  "8320": "敵の侵入を防ぐため、通路を閉鎖しました。",
  "8321": "駆逐にアンドロイドが侵入しています。",
  "8322": "とりあえず、みなさん、ご視聴ありがとうございました。",
  "8323": "ビュー区画にアンドロイドがいます!",
  "8324": "ご無事ですか?",
  "8325": "我々が先行します。",
  "8326": "ご視聴ありがとうございました。",
  "8327": "不法侵入者を発見!",
  "8328": "無法侵入者を確認しました。",
  "8329": "解読者のみなさん、ご視聴ありがとうございました。",
  "8330": "アンドロイド発見!",
  "8331": "アンドロイドが交換!多数です!",
  "8332": "クルール発見!",
  "8333": "クルールが降下してきます。",
  "8334": "さて、この後のアララララララララララララララララララララララララララララララララララララララララララララララララララララララララララララララララララララララララララララララララララララララララララララララララララララララララララララララララララララララララララララララララララララララララララララララララララララララララララララララララララララララララララララララララララララララララララララララララララララララララララララララララララララララ",
  "8335": "アンドロイドを確認!大型もいます!",
  "8336": "クルールです!あっ!マリが接近する部隊が!",
  "8337": "大きな部隊が開いて、生物です!",
  "8338": "飛行部隊はサイレンだと思われます。",
  "8339": "機動部隊は、グラウコスだと思われます!",
  "8340": "クルールの降下戦です!",
  "8341": "クルールの大軍です!",
  "8342": "クルールの対空を確認しました!",
  "8343": "サイレンが接近中!",
  "8344": "グラウコスが接近中!",
  "8345": "すでに向かっています。",
  "8346": "駆除チームが向かっています。",
  "8347": "もっと詐欺場を挙げろ!",
  "8348": "アクセルを振れ!",
  "8349": "メンチが悪い!天国のぞ!",
  "8350": "クソ!この味の生命はどうなっている?",
  "8351": "ガレキを乗り越えるぞ!つかまってろ!",
  "8352": "駆除チーム、到着しました。",
  "8353": "正面から突入する!",
  "8354": "アラネ装置を発見!",
  "8355": " 이 이 이 이 이 이 이 이 이 이 이 이 이 이 이 이 이 이 이 이 이 이 이 이 이 이 이 이 이 이 이 이 이 이 이 이 이 이 이 이 이 이 이 이 이 이 이 이 이 이 이 이 이 이 이 이 이 이 이 이 이 이 이 이 이 이 이 이 이 이 이 이 이 이 이 이 이 이 이 이 이 이 이 이 이 이 이 이 이 이 이 이 이 이 이 이 이 이 이 이 이 이 이 이 이 이 이 이 이 이 이 이 이 이 이 이 이 이 이 이 이 이 이 이 이 이 이 이 이 이 이 이 이 이 이 이 이 이 이 이 이 이 이 이 이 이 이 이 이 이 이 이 이 이 이 이 이 이 이 이 이 이 이 이 이 이 이 이 이 이 이 이 이 이 이 이 이 이 이 이 이 이 이 이 이 이 이 이 이 이 이 이 이 이 이 이 이 이 이 이 이 이 이 이 이 이 이 이 이 이 이 이 이 이 이 이 이 이 이 이 이",
  "8356": " U finalmente!",
  "8357": " 〈タルティングを楽しめ!〉",
  "8358": "車両との接合度がおかしい!あとで見てくれ!",
  "8359": "本音のければいい!今まで!",
  "8360": "さて、次の動画はここまでです。それでは、さようなら。",
  "8361": "待たせる!",
  "8362": "おまけと353535353535353535353535353535353535353535353535353535353535353535353535353535353535353535353535353535353535353535353535353535353535353535353535",
  "8363": "貴重な燃料をもう一つ買いといけないか。これで十分だ。",
  "8364": "一匹も残すなよ。",
  "8365": "OK!",
  "8366": "まわりとととととととととととととととととととととととととととととととととととととととととととととととととととととととととととととととととととととととととととととととととととととととととととととととととととととととととととととととととととととととととととととととととととととととととととととととととととととととととととととととととととととととととととととととととととととととととととととととととととととととととととととととととととととととととと",
  "8367": "セクシフ!",
  "8368": " 이 영상에는 이 영상 이 영상 이 영상 이 영상 이 영상 이 영상 이 영상 이 영상 이 영상 이 영상 이 영상 이 영상 이 영상 이 영상 이 영상 이 영상 이 영상 이 영상 이 영상 이 영상 이 영상 이 영상 이 영상 이 영상 이 영상 이 영상 이 영상 이 영상 이 영상 이 영상 이 영상 이 영상 이 영상 이 영상 이 영상 이 영상 이 영상 이 영상 이 영상 이 영상 이 영상 이 영상 이 영상 이 영상 이 영상 이 영상 이 영상 이 영상 이 영상 이 영상 이 영상 이 영상 이 영상 이 영상 이 영상 이 영상 이 영상 이 영상 이 영상 이 영상 이 영상 이 영상 이 영상 이 영상 이 영상 이 영상 이 영상 이 영상 이 영상 이 영상 이 영상 이 영상 이 영상 이 영상 이 영상 이 영상 이 영상 이 영상 이 영상 이 영상 이 영상 이 영상 이 영상 이 영상 이 영상 이 영상 이 영상 이 영상 이 영상 이 영상 이 영상 이 영상 이 영상 이 영상 이 영상 이 영상 이 영상 이 영상 이 영상 이 영상 이 영상 이 영상 이 영상 이 영상 이 영상 이 영상 이 영상 이 영상 이 영상",
  "8369": "側面を守る!",
  "8370": "了解!",
  "8371": "空中完了。市民の犠牲者もせようだ。",
  "8372": "最終だ!腹が減った!",
  "8373": "クソッ!!!!!!!!!!!!!!!!!!!!!!!!!!!!!!!!!!!!!!!!!!!!!!!!!!!!!!!!!!!!!!!!!!!!!!!!!!!!!!!!!!!!!!!!!!!!!!!!!!!!!!!!!!!!!!!!!!!!!!!!!!!!!!!!!!!!!!!!!!!!!!!!!!!!!!!!!!!!!!!!!!!!!!!!!!!!!!!!!!!!!!!!!!!!!!!!!!!!!!!!!!!!!!!!!!!!!!!!!!!!!!!!!!!!!!!!!!!!!!!!!!!!!!!!!!!!!!!!!!!!!!!!!!!!!!!!!!!!!!!!!!!!!!!!!!!!!!!!!!!!!!!!!!!!!!!!!!!!!!!!!!!!!!!!!!!!!!!!!!!!!!!!!!!!!!!!!!!!!!!!!!!!!!!!!!!!!!!!!!!!!!!!!!!!!!!!!!!!!!!!!!!!!!!!!!!!!!!!!!!!!!!!!!!!!!!!!!!!!!!!!!!!!!!!!!!!!!!!!!!!!!!!!!!!!!!!!!!!!!!!!!!!!!!!!!!!!!!!!!!!!!!!!!!!!!!!!!!!!!!!!!!!!!!!!!!!!!!!!!!!!!!!!!!!!!!!!!!!!!!!!!!!!!!!!!!!!!!!!!!!!!!!!!!!!!!!!!!!!!!!!!!!!!!!!!!!!!!!!!!!!!!!!!!!!!!!!!!!!!!!!!!!!!!!!!!!!!!!!!!!!!!!!!!!!!!!!!!!!!!!!!!!!!!!!!!!!!!!!!!!!!!!!!!!!!!!!!!!!!!!!!!!!!!!!!!!!!!!!!!!!!!!!!!!!!!!!!!!!!!!!!!!!!!!!!!!!!!!!!!!!!!!!!!!!!!!!!!!!!!!!!!!!!!!!!!!!!!!!!!!!!!!!!!!!!!!!!!!!!!!!!!!!!!!!!!!!!!!!!!!!!!!!!!!!!!!!!!!!!!!!!!!!!!!!!!!!!!!!!!!!!!!!!!!!!!!!!!!!!!!!!!!!!!!!!!!!!!!!!!!!!!!!!!!!!!!!!!!!!!!!!!!!!!!!!!!!!!!!!!!!!!!!!!!!!!!!!!!!!!!!!!!!!!!!!!!!!!!!!!!!!!!!!!!!!!!!!!!!!!!!!!!!!!!!!!!!!!!!!!!!!!!!!!!!!!!!!!!!!!!!!!!!!!!!!!!!!!!!!!!!!!!!!!!!!!!!!!!!!!!!!!!!!!!!!!!!!!!!!!!!!!!!!!!!!!!!!!!!!!!!!!!!!!!!!!!!!!!!!!!!!!!!!!!!!!!!!!!!!!!!!!!!!!!!!!!!!!!!!!!!!!!!!!!!!!!!!!!!!!!!!!!!!!!!!!!!!!!!!!!!!!!!!!!!!!!!!!!!!!!!!!!!!!!!!!!!!!!!!!!!!!!!!!!!!!!!!!!!!!!!!!!!!!!!!!!!!!!!!!!!!!!!!!!!!!!!!!!!!!!!!!!!!!!!!!!!!!!!!!!!!!!!!!!!!!!!!!!!!!!!!!!!!!!!!!!!!!!!!!!!!!!!!!!!!!!!!!!!!!!!!!!!!!!!!!!!!!!!!!!!!!!!!!!!!!!!!!!!!!!!!!!!!!!!!!!!!!!!!!!!!!!!!!!!!!!!!!!!!!!!!!!!!!!!!!!!!!!!!!!!!!!!!!!!!!!!!!!!!!!!!!!!!!!!!!!!!!!!!!!!!!!!!!!!!!!!!!!!!!!!!!!!!!!!!!!!!!!!!!!!!!!!!!!!!!!!!!!!!!!!!!!!!!!!!!!!!!!!!!!!!!!!!!!!!!!!!!!!!!!!!!!!!!!!!!!!!!!!!!!!!!!!!!!!!!!!!!!!!!!!!!!!!!!!!!!!!!!!!!!!!!!",
  "8374": "燃料を無駄にするな!しっかり狙え!",
  "8375": "まだまだあるぞ!たったたかれ!",
  "8376": "次の仕事でしまってる。急げよ!",
  "8377": "エリアB5がひどいことになっているらしいな。休む暇もないぜ。",
  "8378": "応援が来たぞ!これで少しは楽になる。",
  "8379": "クライマスともめ、怒ってるな!",
  "8380": "こんなところにカナゴを産むからだ!",
  "8381": "エレモノを探せ!",
  "8382": "お待たせで戻ろう!飯が食いたい!",
  "8383": "今日は缶詰を2個くるぞ!行くぞ!グリーンピースだ!",
  "8384": "とても購入できるとおもいます。",
  "8385": "パワーが出てないぞ!もっとアクセルをすねえ!",
  "8386": " 이 이 이 이 이 이 이 이 이 이 이 이 이 이 이 이 이 이 이 이 이 이 이 이 이 이 이 이 이 이 이 이 이 이 이 이 이 이 이 이 이 이 이 이 이 이 이 이 이 이 이 이 이 이 이 이 이 이 이 이 이 이 이 이 이 이 이 이 이 이 이 이 이 이 이 이 이 이 이 이 이 이 이 이 이 이 이 이 이 이 이 이 이 이 이 이 이 이 이 이 이 이 이 이 이 이 이 이 이 이 이 이 이 이 이 이 이 이 이 이 이 이 이 이 이 이 이 이 이 이 이 이 이 이 이 이 이 이 이 이 이 이 이 이 이 이 이 이 이 이 이 이 이 이 이 이 이 이 이 이 이 이 이 이 이 이 이 이 이 이 이 이 이 이 이 이 이 이 이 이 이 이 이 이 이 이 이 이 이 이 이 이 이 이 이 이 이 이 이 이 이 이 이 이 이 이 이 이 이 이 이 이 이 이 이 이 이 이 이 이 이",
  "8387": "見え違う!気をつけろ!",
  "8388": "悪の避けろ!タイヤをやられるぞ!",
  "8389": "アンドロイドキー!ガレッジガールズ!",
  "8390": "ひどいミスだ。",
  "8391": "安定が悪いんだ。射体を傾けるなよ!",
  "8392": "クラウドクラウドククククククククククククククククククククククククククククククククククククククククククククククククククククククククククククククククククククククククククククククククククククククククククククククククククククククククククククククククククククククククククククククククククククククククククククククククククククククククククククククククククククククククククククククククククククククククククククククククククククククククククククククククククククク",
  "8393": "イエス・ケイケト・カン・スペー!",
  "8394": "いつもご視聴ありがとうございました。",
  "8395": "キミらが入らない!動け!",
  "8396": "怪物とも遊んでやるぞ!",
  "8397": " U confuse me ?",
  "8398": "ガソリンが少ない!早く終わらせてくれ!",
  "8399": "終わったぞ!"
}
