{
  "23300": "やばい!くらった!",
  "23301": " ultimate ultimate ultimate ultimate ultimate ultimate ultimate ultimate ultimate ultimate ultimate ultimate ultimate ultimate ultimate ultimate ultimate ultimate ultimate ultimate ultimate ultimate ultimate ultimate ultimate ultimate ultimate ultimate ultimate ultimate ultimate ultimate ultimate ultimate ultimate ultimate ultimate ultimate ultimate ultimate ultimate ultimate ultimate ultimate ultimate ultimate ultimate ultimate ultimate ultimate ultimate ultimate ultimate ultimate ultimate ultimate ultimate ultimate ultimate ultimate ultimate ultimate ultimate ultimate ultimate ultimate ultimate ultimate ultimate ultimate ultimate ultimate ultimate ultimate ultimate ultimate ultimate ultimate ultimate ultimate ultimate ultimate ultimate ultimate ultimate ultimate ultimate ultimate ultimate ultimate ultimate ultimate ultimate ultimate ultimate ultimate ultimate ultimate ultimate ultimate ultimate ultimate ultimate ultimate ultimate ultimate ultimate ultimate ultimate ultimate ultimate ultimate ultimate ultimate ultimate ultimate ultimate ultimate ultimate ultimate ultimate ultimate ultimate ultimate ultimate ultimate ultimate ultimate ultimate ultimate ultimate ultimate ultimate ultimate ultimate ultimate ultimate ultimate ultimate ultimate ultimate ultimate ultimate ultimate ultimate ultimate ultimate ultimate ultimate ultimate ultimate ultimate ultimate ultimate ultimate ultimate ultimate ultimate ultimate ultimate ultimate ultimate ultimate ultimate ultimate ultimate ultimate ultimate ultimate ultimate ultimate ultimate ultimate ultimate ultimate ultimate ultimate ultimate ultimate ultimate ultimate ultimate ultimate ultimate ultimate ultimate ultimate ultimate ultimate ultimate ultimate ultimate ultimate ultimate ultimate ultimate ultimate ultimate ultimate ultimate ultimate ultimate ultimate ultimate ultimate ultimate ultimate ultimate ultimate ultimate ultimate ultimate ultimate ultimate ultimate ultimate ultimate ultimate ultimate ultimate ultimate",
  "23302": " ¯罌 ¯",
  "23303": " ultimate",
  "23304": "wwwww",
  "23305": "yrtetetetetetetetetetetetetetete",
  "23306": " ultimateteeteeteeteeteeteeteeteeteetee",
  "23307": "大将!",
  "23308": "まずい!隊長がやられた!",
  "23309": "大将（!（は敵を撃ちます!",
  "23310": "会長!返事をしてください!",
  "23311": " ultimate",
  "23312": " ultimate ultimate ultimate ultimate ultimate ultimate ultimate ultimate ultimate ultimate",
  "23313": " ultimate ultimate ultimate ultimate ultimate ultimate ultimate ultimate ultimate ultimate ultimate",
  "23314": "良い隊長だった!",
  "23315": "忘れないぜ、隊長!",
  "23316": "代わりの指揮官が必要だ!",
  "23317": " ultimate ultimate ultimate ultimate ultimate ultimate ultimate ultimate ultimate ultimate ultimate ultimate ultimate ultimate ultimate ultimate ultimate ultimate ultimate ultimate ultimate ultimate ultimate ultimate ultimate ultimate ultimate ultimate ultimate ultimate ultimate ultimate ultimate ultimate ultimate ultimate ultimate ultimate ultimate ultimate ultimate ultimate ultimate ultimate ultimate ultimate ultimate ultimate ultimate ultimate ultimate ultimate ultimate ultimate ultimate ultimate ultimate ultimate ultimate ultimate ultimate ultimate ultimate ultimate ultimate ultimate ultimate ultimate ultimate ultimate ultimate ultimate ultimate ultimate ultimate ultimate ultimate ultimate ultimate ultimate ultimate ultimate ultimate ultimate ultimate ultimate ultimate ultimate ultimate ultimate ultimate ultimate ultimate ultimate ultimate ultimate ultimate ultimate ultimate ultimate ultimate ultimate ultimate ultimate ultimate ultimate ultimate ultimate ultimate ultimate ultimate ultimate ultimate ultimate ultimate ultimate ultimate ultimate ultimate ultimate ultimate ultimate ultimate ultimate ultimate ultimate ultimate ultimate ultimate ultimate ultimate ultimate ultimate ultimate ultimate ultimate ultimate ultimate ultimate ultimate ultimate ultimate ultimate ultimate ultimate ultimate ultimate ultimate ultimate ultimate ultimate ultimate ultimate ultimate ultimate ultimate ultimate ultimate ultimate ultimate ultimate ultimate ultimate ultimate ultimate ultimate ultimate ultimate ultimate ultimate ultimate ultimate ultimate ultimate ultimate ultimate ultimate ultimate ultimate ultimate ultimate ultimate ultimate ultimate ultimate ultimate ultimate ultimate ultimate ultimate ultimate ultimate ultimate ultimate ultimate ultimate ultimate ultimate ultimate ultimate ultimate ultimate ultimate ultimate ultimate ultimate ultimate ultimate ultimate ultimate ultimate ultimate ultimate ultimate ultimate ultimate ultimate ultimate ultimate ultimate ultimate",
  "23318": "一人死にました!",
  "23319": "一人やられました!",
  "23320": "一命戦死!",
  "23321": "一人やられた!",
  "23322": "次回予告",
  "23323": "仲間が!",
  "23324": "誰か倒れたぞ!",
  "23325": "仲間がやられた!",
  "23326": "だちが…くそ!",
  "23327": "おまえよ!戦友!",
  "23328": " ultimate ultimate ultimate ultimate ultimate ultimate ultimate ultimate ultimate ultimate ultimate ultimate ultimate ultimate ultimate ultimate ultimate ultimate ultimate ultimate ultimate ultimate ultimate ultimate ultimate ultimate ultimate ultimate ultimate ultimate ultimate ultimate ultimate ultimate ultimate ultimate ultimate ultimate ultimate ultimate ultimate ultimate ultimate ultimate ultimate ultimate ultimate ultimate ultimate ultimate ultimate ultimate ultimate ultimate ultimate ultimate ultimate ultimate ultimate ultimate ultimate ultimate ultimate ultimate ultimate ultimate ultimate ultimate ultimate ultimate ultimate ultimate ultimate ultimate ultimate ultimate ultimate ultimate ultimate ultimate ultimate ultimate ultimate ultimate ultimate ultimate ultimate ultimate ultimate ultimate ultimate ultimate ultimate ultimate ultimate ultimate ultimate ultimate ultimate ultimate ultimate ultimate ultimate ultimate ultimate ultimate ultimate ultimate ultimate ultimate ultimate ultimate ultimate ultimate ultimate ultimate ultimate ultimate ultimate ultimate ultimate ultimate ultimate ultimate ultimate ultimate ultimate ultimate ultimate ultimate ultimate ultimate ultimate ultimate ultimate ultimate ultimate ultimate ultimate ultimate ultimate ultimate ultimate ultimate ultimate ultimate ultimate ultimate ultimate ultimate ultimate ultimate ultimate ultimate ultimate ultimate ultimate ultimate ultimate ultimate ultimate ultimate ultimate ultimate ultimate ultimate ultimate ultimate ultimate ultimate ultimate ultimate ultimate ultimate ultimate ultimate ultimate ultimate ultimate ultimate ultimate ultimate ultimate ultimate ultimate ultimate ultimate ultimate ultimate ultimate ultimate ultimate ultimate ultimate ultimate ultimate ultimate ultimate ultimate ultimate ultimate ultimate ultimate ultimate ultimate ultimate ultimate ultimate ultimate ultimate ultimate ultimate ultimate ultimate ultimate ultimate ultimate ultimate ultimate ultimate ultimate",
  "23329": " ultimate ultimate ultimate ultimate ultimate ultimate ultimate ultimate ultimate ultimate ultimate ultimate ultimate ultimate ultimate ultimate ultimate ultimate ultimate ultimate ultimate ultimate ultimate ultimate ultimate ultimate ultimate ultimate ultimate ultimate ultimate ultimate ultimate ultimate ultimate ultimate ultimate ultimate ultimate ultimate ultimate ultimate ultimate ultimate ultimate ultimate ultimate ultimate ultimate ultimate ultimate ultimate ultimate ultimate ultimate ultimate ultimate ultimate ultimate ultimate ultimate ultimate ultimate ultimate ultimate ultimate ultimate ultimate ultimate ultimate ultimate ultimate ultimate ultimate ultimate ultimate ultimate ultimate ultimate ultimate ultimate ultimate ultimate ultimate ultimate ultimate ultimate ultimate ultimate ultimate ultimate ultimate ultimate ultimate ultimate ultimate ultimate ultimate ultimate ultimate ultimate ultimate ultimate ultimate ultimate ultimate ultimate ultimate ultimate ultimate ultimate ultimate ultimate ultimate ultimate ultimate ultimate ultimate ultimate ultimate ultimate ultimate ultimate ultimate ultimate ultimate ultimate ultimate ultimate ultimate ultimate ultimate ultimate ultimate ultimate ultimate ultimate ultimate ultimate ultimate ultimate ultimate ultimate ultimate ultimate ultimate ultimate ultimate ultimate ultimate ultimate ultimate ultimate ultimate ultimate ultimate ultimate ultimate ultimate ultimate ultimate ultimate ultimate ultimate ultimate ultimate ultimate ultimate ultimate ultimate ultimate ultimate ultimate ultimate ultimate ultimate ultimate ultimate ultimate ultimate ultimate ultimate ultimate ultimate ultimate ultimate ultimate ultimate ultimate ultimate ultimate ultimate ultimate ultimate ultimate ultimate ultimate ultimate ultimate ultimate ultimate ultimate ultimate ultimate ultimate ultimate ultimate ultimate ultimate ultimate ultimate ultimate ultimate ultimate ultimate ultimate ultimate ultimate ultimate ultimate ultimate",
  "23330": " ultimate ultimate ultimate ultimate ultimate ultimate ultimate ultimate ultimate ultimate ultimate ultimate ultimate ultimate ultimate ultimate ultimate ultimate ultimate ultimate ultimate ultimate ultimate ultimate ultimate ultimate ultimate ultimate ultimate ultimate ultimate ultimate ultimate ultimate ultimate ultimate ultimate ultimate ultimate ultimate ultimate ultimate ultimate ultimate ultimate ultimate ultimate ultimate ultimate ultimate ultimate ultimate ultimate ultimate ultimate ultimate ultimate ultimate ultimate ultimate ultimate ultimate ultimate ultimate ultimate ultimate ultimate ultimate ultimate ultimate ultimate ultimate ultimate ultimate ultimate ultimate ultimate ultimate ultimate ultimate ultimate ultimate ultimate ultimate ultimate ultimate ultimate ultimate ultimate ultimate ultimate ultimate ultimate ultimate ultimate ultimate ultimate ultimate ultimate ultimate ultimate ultimate ultimate ultimate ultimate ultimate ultimate ultimate ultimate ultimate ultimate ultimate ultimate ultimate ultimate ultimate ultimate ultimate ultimate ultimate ultimate ultimate ultimate ultimate ultimate ultimate ultimate ultimate ultimate ultimate ultimate ultimate ultimate ultimate ultimate ultimate ultimate ultimate ultimate ultimate ultimate ultimate ultimate ultimate ultimate ultimate ultimate ultimate ultimate ultimate ultimate ultimate ultimate ultimate ultimate ultimate ultimate ultimate ultimate ultimate ultimate ultimate ultimate ultimate ultimate ultimate ultimate ultimate ultimate ultimate ultimate ultimate ultimate ultimate ultimate ultimate ultimate ultimate ultimate ultimate ultimate ultimate ultimate ultimate ultimate ultimate ultimate ultimate ultimate ultimate ultimate ultimate ultimate ultimate ultimate ultimate ultimate ultimate ultimate ultimate ultimate ultimate ultimate ultimate ultimate ultimate ultimate ultimate ultimate ultimate ultimate ultimate ultimate ultimate ultimate ultimate ultimate ultimate ultimate ultimate ultimate",
  "23331": " ultimate ultimate ultimate ultimate ultimate ultimate ultimate ultimate ultimate ultimate ultimate",
  "23332": "よくも仲間を殺したな!",
  "23333": "先輩（なんてこと!",
  "23334": "次回はお楽しみに!",
  "23335": "おーい!生きてるか!",
  "23336": "先遊、地獄で会おう!",
  "23337": "うぅぅぅぅぅぅぅぅぅぅぅぅぅぅぅぅぅぅぅぅぅぅぅぅぅぅぅぅぅぅぅぅぅぅぅぅぅぅぅぅぅぅぅぅぅぅぅぅぅぅぅぅぅぅぅぅぅぅぅぅぅぅぅぅぅぅぅぅぅぅぅぅぅぅぅぅぅぅぅぅぅぅぅぅぅぅぅぅぅぅぅぅぅぅぅぅぅぅぅぅぅぅぅぅぅぅぅぅぅぅ",
  "23338": " ¯罌 ¯",
  "23339": " ultimate",
  "23340": "やめてくれ!",
  "23341": "しまった!",
  "23342": "助けてくれ!",
  "23343": "シックシック!離せ!",
  "23344": "放せ!放せ!",
  "23345": " ultimateteeteeteeteeteeteeteeteeteeteetee",
  "23346": "何とかしてくれ!",
  "23347": "死にたくない!",
  "23348": "この人を撃ってくれ!",
  "23349": "見てないで助けろ!",
  "23350": " ultimate ultimate ultimate ultimate ultimate ultimate ultimate ultimate ultimate ultimate ultimate ultimate ultimate ultimate ultimate ultimate ultimate ultimate ultimate ultimate ultimate ultimate ultimate ultimate ultimate ultimate ultimate ultimate ultimate ultimate ultimate ultimate ultimate ultimate ultimate ultimate ultimate ultimate ultimate ultimate ultimate ultimate ultimate ultimate ultimate ultimate ultimate ultimate ultimate ultimate ultimate ultimate ultimate ultimate ultimate ultimate ultimate ultimate ultimate ultimate ultimate ultimate ultimate ultimate ultimate ultimate ultimate ultimate ultimate ultimate ultimate ultimate ultimate ultimate ultimate ultimate ultimate ultimate ultimate ultimate ultimate ultimate ultimate ultimate ultimate ultimate ultimate ultimate ultimate ultimate ultimate ultimate ultimate ultimate ultimate ultimate ultimate ultimate ultimate ultimate ultimate ultimate ultimate ultimate ultimate ultimate ultimate ultimate ultimate ultimate ultimate ultimate ultimate ultimate ultimate ultimate ultimate ultimate ultimate ultimate ultimate ultimate ultimate ultimate ultimate ultimate ultimate ultimate ultimate ultimate ultimate ultimate ultimate ultimate ultimate ultimate ultimate ultimate ultimate ultimate ultimate ultimate ultimate ultimate ultimate ultimate ultimate ultimate ultimate ultimate ultimate ultimate ultimate ultimate ultimate ultimate ultimate ultimate ultimate ultimate ultimate ultimate ultimate ultimate ultimate ultimate ultimate ultimate ultimate ultimate ultimate ultimate ultimate ultimate ultimate ultimate ultimate ultimate ultimate ultimate ultimate ultimate ultimate ultimate ultimate ultimate ultimate ultimate ultimate ultimate ultimate ultimate ultimate ultimate ultimate ultimate ultimate ultimate ultimate ultimate ultimate ultimate ultimate ultimate ultimate ultimate ultimate ultimate ultimate ultimate ultimate ultimate ultimate ultimate ultimate ultimate ultimate ultimate ultimate ultimate ultimate",
  "23351": " ultimate ultimate ultimate ultimate ultimate ultimate ultimate ultimate ultimate ultimate ultimate ultimate ultimate ultimate ultimate ultimate ultimate ultimate ultimate ultimate ultimate ultimate ultimate ultimate ultimate ultimate ultimate ultimate ultimate ultimate ultimate ultimate ultimate ultimate ultimate ultimate ultimate ultimate ultimate ultimate ultimate ultimate ultimate ultimate ultimate ultimate ultimate ultimate ultimate ultimate ultimate ultimate ultimate ultimate ultimate ultimate ultimate ultimate ultimate ultimate ultimate ultimate ultimate ultimate ultimate ultimate ultimate ultimate ultimate ultimate ultimate ultimate ultimate ultimate ultimate ultimate ultimate ultimate ultimate ultimate ultimate ultimate ultimate ultimate ultimate ultimate ultimate ultimate ultimate ultimate ultimate ultimate ultimate ultimate ultimate ultimate ultimate ultimate ultimate ultimate ultimate ultimate ultimate ultimate ultimate ultimate ultimate ultimate ultimate ultimate ultimate ultimate ultimate ultimate ultimate ultimate ultimate ultimate ultimate ultimate ultimate ultimate ultimate ultimate ultimate ultimate ultimate ultimate ultimate ultimate ultimate ultimate ultimate ultimate ultimate ultimate ultimate ultimate ultimate ultimate ultimate ultimate ultimate ultimate ultimate ultimate ultimate ultimate ultimate ultimate ultimate ultimate ultimate ultimate ultimate ultimate ultimate ultimate ultimate ultimate ultimate ultimate ultimate ultimate ultimate ultimate ultimate ultimate ultimate ultimate ultimate ultimate ultimate ultimate ultimate ultimate ultimate ultimate ultimate ultimate ultimate ultimate ultimate ultimate ultimate ultimate ultimate ultimate ultimate ultimate ultimate ultimate ultimate ultimate ultimate ultimate ultimate ultimate ultimate ultimate ultimate ultimate ultimate ultimate ultimate ultimate ultimate ultimate ultimate ultimate ultimate ultimate ultimate ultimate ultimate ultimate ultimate ultimate ultimate ultimate ultimate",
  "23352": "引っ張られる!すごい力だ!",
  "23353": "イエスに捕まった!助けてくれ!",
  "23354": "クソ!いいとこが!",
  "23355": "イントが、援護してくれ!",
  "23356": "次回はまたお楽しみに!",
  "23357": "次回はまたお楽しみに!",
  "23358": " ultimateteeteeteeteeteeteeteeteeteetee",
  "23359": "次回予告",
  "23360": "放せ!放せ!",
  "23361": "クシュー!ハズレナイゾ!",
  "23362": "動けない!誰か!",
  "23363": "次回はお楽しみに!",
  "23364": " ultimate ultimate ultimate ultimate ultimate ultimate ultimate ultimate ultimate ultimate ultimate",
  "23365": "ネットの上だ!助けてくれ!",
  "23366": "次回はお楽しみに!",
  "23367": "次回はお楽しみに!",
  "23368": " ultimateteeteeteeteeteeteeteeteeteetee",
  "23369": "レッドに引っかかった奴がいる!",
  "23370": "アミの上に誰かいる!助けろ!",
  "23371": "最後に助けてやるぞ!",
  "23372": "少年の少年の少年の少年の少年の少年の少年の少年の少年の少年の少年の少年の少年の少年の少年の少年の少年の少年の少年の少年の少年の少年の少年の少年の少年の少年の少年の少年の少年の少年の少年の少年の少年の少年の少年の少年の少年の少年の少年の少年の少年の少年の少年の少年の少年の少年の少年の少年の少年の少年の少年の少年の少年の少年の少年の少年の少年の少年の少年の少年の少年の少年の少年の少年の少年の少年の少年の少年の少年の少年の少年の少年の少年の少年",
  "23373": "見捨てないぞ!網を破壊しよう!",
  "23374": " ultimate ultimate ultimate ultimate ultimate ultimate ultimate ultimate ultimate ultimate ultimate ultimate ultimate ultimate ultimate ultimate ultimate ultimate ultimate ultimate ultimate ultimate ultimate ultimate ultimate ultimate ultimate ultimate ultimate ultimate ultimate ultimate ultimate ultimate ultimate ultimate ultimate ultimate ultimate ultimate ultimate ultimate ultimate ultimate ultimate ultimate ultimate ultimate ultimate ultimate ultimate ultimate ultimate ultimate ultimate ultimate ultimate ultimate ultimate ultimate ultimate ultimate ultimate ultimate ultimate ultimate ultimate ultimate ultimate ultimate ultimate ultimate ultimate ultimate ultimate ultimate ultimate ultimate ultimate ultimate ultimate ultimate ultimate ultimate ultimate ultimate ultimate ultimate ultimate ultimate ultimate ultimate ultimate ultimate ultimate ultimate ultimate ultimate ultimate ultimate ultimate ultimate ultimate ultimate ultimate ultimate ultimate ultimate ultimate ultimate ultimate ultimate ultimate ultimate ultimate ultimate ultimate ultimate ultimate ultimate ultimate ultimate ultimate ultimate ultimate ultimate ultimate ultimate ultimate ultimate ultimate ultimate ultimate ultimate ultimate ultimate ultimate ultimate ultimate ultimate ultimate ultimate ultimate ultimate ultimate ultimate ultimate ultimate ultimate ultimate ultimate ultimate ultimate ultimate ultimate ultimate ultimate ultimate ultimate ultimate ultimate ultimate ultimate ultimate ultimate ultimate ultimate ultimate ultimate ultimate ultimate ultimate ultimate ultimate ultimate ultimate ultimate ultimate ultimate ultimate ultimate ultimate ultimate ultimate ultimate ultimate ultimate ultimate ultimate ultimate ultimate ultimate ultimate ultimate ultimate ultimate ultimate ultimate ultimate ultimate ultimate ultimate ultimate ultimate ultimate ultimate ultimate ultimate ultimate ultimate ultimate ultimate ultimate ultimate ultimate ultimate ultimate ultimate ultimate ultimate ultimate",
  "23375": "ネットに!救助しよう!",
  "23376": "感謝する!恩人だ!",
  "23377": "持つべきものは潜入だ!",
  "23378": "お前のおかげで助かった!",
  "23379": "ネットを破壊したのは誰だ?感謝する!",
  "23380": "自由だ!助かった!",
  "23381": "良い仕事だ!命拾いした!",
  "23382": " ultimate ultimate ultimate ultimate ultimate ultimate ultimate ultimate ultimate ultimate ultimate ultimate ultimate ultimate ultimate ultimate ultimate ultimate ultimate ultimate ultimate ultimate ultimate ultimate ultimate ultimate ultimate ultimate ultimate ultimate ultimate ultimate ultimate ultimate ultimate ultimate ultimate ultimate ultimate ultimate ultimate ultimate ultimate ultimate ultimate ultimate ultimate ultimate ultimate ultimate ultimate ultimate ultimate ultimate ultimate ultimate ultimate ultimate ultimate ultimate ultimate ultimate ultimate ultimate ultimate ultimate ultimate ultimate ultimate ultimate ultimate ultimate ultimate ultimate ultimate ultimate ultimate ultimate ultimate ultimate ultimate ultimate ultimate ultimate ultimate ultimate ultimate ultimate ultimate ultimate ultimate ultimate ultimate ultimate ultimate ultimate ultimate ultimate ultimate ultimate ultimate ultimate ultimate ultimate ultimate ultimate ultimate ultimate ultimate ultimate ultimate ultimate ultimate ultimate ultimate ultimate ultimate ultimate ultimate ultimate ultimate ultimate ultimate ultimate ultimate ultimate ultimate ultimate ultimate ultimate ultimate ultimate ultimate ultimate ultimate ultimate ultimate ultimate ultimate ultimate ultimate ultimate ultimate ultimate ultimate ultimate ultimate ultimate ultimate ultimate ultimate ultimate ultimate ultimate ultimate ultimate ultimate ultimate ultimate ultimate ultimate ultimate ultimate ultimate ultimate ultimate ultimate ultimate ultimate ultimate ultimate ultimate ultimate ultimate ultimate ultimate ultimate ultimate ultimate ultimate ultimate ultimate ultimate ultimate ultimate ultimate ultimate ultimate ultimate ultimate ultimate ultimate ultimate ultimate ultimate ultimate ultimate ultimate ultimate ultimate ultimate ultimate ultimate ultimate ultimate ultimate ultimate ultimate ultimate ultimate ultimate ultimate ultimate ultimate ultimate ultimate ultimate ultimate ultimate ultimate ultimate",
  "23383": "自由だ!助かった!",
  "23384": "誰がネットを破壊したのだ?感謝する!",
  "23385": "持つべき者は戦友だ!",
  "23386": "お前のおかげで助かった!",
  "23387": "感謝する!本人だ!",
  "23388": "レッドに救助しよう!",
  "23389": "見捨てないぞ!網を破壊しよう!",
  "23390": " ultimate ultimate ultimate ultimate ultimate ultimate ultimate ultimate ultimate ultimate ultimate ultimate ultimate ultimate ultimate ultimate ultimate ultimate ultimate ultimate ultimate ultimate ultimate ultimate ultimate ultimate ultimate ultimate ultimate ultimate ultimate ultimate ultimate ultimate ultimate ultimate ultimate ultimate ultimate ultimate ultimate ultimate ultimate ultimate ultimate ultimate ultimate ultimate ultimate ultimate ultimate ultimate ultimate ultimate ultimate ultimate ultimate ultimate ultimate ultimate ultimate ultimate ultimate ultimate ultimate ultimate ultimate ultimate ultimate ultimate ultimate ultimate ultimate ultimate ultimate ultimate ultimate ultimate ultimate ultimate ultimate ultimate ultimate ultimate ultimate ultimate ultimate ultimate ultimate ultimate ultimate ultimate ultimate ultimate ultimate ultimate ultimate ultimate ultimate ultimate ultimate ultimate ultimate ultimate ultimate ultimate ultimate ultimate ultimate ultimate ultimate ultimate ultimate ultimate ultimate ultimate ultimate ultimate ultimate ultimate ultimate ultimate ultimate ultimate ultimate ultimate ultimate ultimate ultimate ultimate ultimate ultimate ultimate ultimate ultimate ultimate ultimate ultimate ultimate ultimate ultimate ultimate ultimate ultimate ultimate ultimate ultimate ultimate ultimate ultimate ultimate ultimate ultimate ultimate ultimate ultimate ultimate ultimate ultimate ultimate ultimate ultimate ultimate ultimate ultimate ultimate ultimate ultimate ultimate ultimate ultimate ultimate ultimate ultimate ultimate ultimate ultimate ultimate ultimate ultimate ultimate ultimate ultimate ultimate ultimate ultimate ultimate ultimate ultimate ultimate ultimate ultimate ultimate ultimate ultimate ultimate ultimate ultimate ultimate ultimate ultimate ultimate ultimate ultimate ultimate ultimate ultimate ultimate ultimate ultimate ultimate ultimate ultimate ultimate ultimate ultimate ultimate ultimate ultimate ultimate ultimate",
  "23391": "すぐに助けてやるぞ!",
  "23392": " ultimate ultimate ultimate ultimate ultimate ultimate ultimate ultimate ultimate ultimate ultimate ultimate ultimate ultimate ultimate ultimate ultimate ultimate ultimate ultimate ultimate ultimate ultimate ultimate ultimate ultimate ultimate ultimate ultimate ultimate ultimate ultimate ultimate ultimate ultimate ultimate ultimate ultimate ultimate ultimate ultimate ultimate ultimate ultimate ultimate ultimate ultimate ultimate ultimate ultimate ultimate ultimate ultimate ultimate ultimate ultimate ultimate ultimate ultimate ultimate ultimate ultimate ultimate ultimate ultimate ultimate ultimate ultimate ultimate ultimate ultimate ultimate ultimate ultimate ultimate ultimate ultimate ultimate ultimate ultimate ultimate ultimate ultimate ultimate ultimate ultimate ultimate ultimate ultimate ultimate ultimate ultimate ultimate ultimate ultimate ultimate ultimate ultimate ultimate ultimate ultimate ultimate ultimate ultimate ultimate ultimate ultimate ultimate ultimate ultimate ultimate ultimate ultimate ultimate ultimate ultimate ultimate ultimate ultimate ultimate ultimate ultimate ultimate ultimate ultimate ultimate ultimate ultimate ultimate ultimate ultimate ultimate ultimate ultimate ultimate ultimate ultimate ultimate ultimate ultimate ultimate ultimate ultimate ultimate ultimate ultimate ultimate ultimate ultimate ultimate ultimate ultimate ultimate ultimate ultimate ultimate ultimate ultimate ultimate ultimate ultimate ultimate ultimate ultimate ultimate ultimate ultimate ultimate ultimate ultimate ultimate ultimate ultimate ultimate ultimate ultimate ultimate ultimate ultimate ultimate ultimate ultimate ultimate ultimate ultimate ultimate ultimate ultimate ultimate ultimate ultimate ultimate ultimate ultimate ultimate ultimate ultimate ultimate ultimate ultimate ultimate ultimate ultimate ultimate ultimate ultimate ultimate ultimate ultimate ultimate ultimate ultimate ultimate ultimate ultimate ultimate ultimate ultimate ultimate ultimate ultimate",
  "23393": "メットに引っ掛かった奴がいる!",
  "23394": " ultimate ultimate ultimate ultimate ultimate ultimate ultimate ultimate ultimate ultimate ultimate ultimate ultimate ultimate ultimate ultimate ultimate ultimate ultimate ultimate ultimate ultimate ultimate ultimate ultimate ultimate ultimate ultimate ultimate ultimate ultimate ultimate ultimate ultimate ultimate ultimate ultimate ultimate ultimate ultimate ultimate ultimate ultimate ultimate ultimate ultimate ultimate ultimate ultimate ultimate ultimate ultimate ultimate ultimate ultimate ultimate ultimate ultimate ultimate ultimate ultimate ultimate ultimate ultimate ultimate ultimate ultimate ultimate ultimate ultimate ultimate ultimate ultimate ultimate ultimate ultimate ultimate ultimate ultimate ultimate ultimate ultimate ultimate ultimate ultimate ultimate ultimate ultimate ultimate ultimate ultimate ultimate ultimate ultimate ultimate ultimate ultimate ultimate ultimate ultimate ultimate ultimate ultimate ultimate ultimate ultimate ultimate ultimate ultimate ultimate ultimate ultimate ultimate ultimate ultimate ultimate ultimate ultimate ultimate ultimate ultimate ultimate ultimate ultimate ultimate ultimate ultimate ultimate ultimate ultimate ultimate ultimate ultimate ultimate ultimate ultimate ultimate ultimate ultimate ultimate ultimate ultimate ultimate ultimate ultimate ultimate ultimate ultimate ultimate ultimate ultimate ultimate ultimate ultimate ultimate ultimate ultimate ultimate ultimate ultimate ultimate ultimate ultimate ultimate ultimate ultimate ultimate ultimate ultimate ultimate ultimate ultimate ultimate ultimate ultimate ultimate ultimate ultimate ultimate ultimate ultimate ultimate ultimate ultimate ultimate ultimate ultimate ultimate ultimate ultimate ultimate ultimate ultimate ultimate ultimate ultimate ultimate ultimate ultimate ultimate ultimate ultimate ultimate ultimate ultimate ultimate ultimate ultimate ultimate ultimate ultimate ultimate ultimate ultimate ultimate ultimate ultimate ultimate ultimate ultimate ultimate",
  "23395": "あみを壊してくれ!",
  "23396": "次回予告",
  "23397": "※ネットの上だ!助けてくれ!",
  "23398": " ultimate を破壊したくらtee",
  "23399": " ultimate ultimate ultimate ultimate ultimate ultimate ultimate ultimate ultimate ultimate ultimate"
}